actinia_cloudevent_plugin/__init__.py
actinia_cloudevent_plugin/endpoints.py
actinia_cloudevent_plugin/main.py
actinia_cloudevent_plugin/api/__init__.py
actinia_cloudevent_plugin/api/cloudevent.py
actinia_cloudevent_plugin/apidocs/__init__.py
actinia_cloudevent_plugin/apidocs/cloudevent.py
actinia_cloudevent_plugin/core/__init__.py
actinia_cloudevent_plugin/core/processing.py
actinia_cloudevent_plugin/model/__init__.py
actinia_cloudevent_plugin/model/response_models.py
actinia_cloudevent_plugin/resources/__init__.py
actinia_cloudevent_plugin/resources/config.py
actinia_cloudevent_plugin/resources/logging.py
actinia_cloudevent_plugin-0.1.0.dist-info/licenses/LICENSE.txt
actinia_cloudevent_plugin-0.1.0.dist-info/METADATA
actinia_cloudevent_plugin-0.1.0.dist-info/WHEEL
actinia_cloudevent_plugin-0.1.0.dist-info/top_level.txt
actinia_cloudevent_plugin-0.1.0.dist-info/RECORD
