Metadata-Version: 2.4
Name: actinia-cloudevent-plugin
Version: 0.1.0
Summary: An actinia-core plugin which adds example endpoints to actinia-core
Author: Carmen Tawalika, Anika Weinmann
Project-URL: Homepage, https://github.com/mundialis/actinia-cloudevent-plugin
Project-URL: Tutorial, https://mundialis.github.io/actinia_core
Project-URL: API_Docs, https://redocly.github.io/redoc/?url=https://actinia.mundialis.de/latest/swagger.json
Keywords: processing,earth observation,cloud-based processing,rest api,gis,grass gis,osgeo,example
Classifier: License :: OSI Approved :: Apache Software License
Classifier: Programming Language :: Python :: 3
Requires-Python: >=3.8
License-File: LICENSE.txt
Requires-Dist: Flask
Requires-Dist: Flask-Cors>=3.0.3
Requires-Dist: flask-restful-swagger-2>=0.35
Requires-Dist: colorlog>=3.1.4
Requires-Dist: python-json-logger
Requires-Dist: requests>=2.20.0
Requires-Dist: cloudevents
Provides-Extra: test
Requires-Dist: pytest; extra == "test"
Requires-Dist: pytest-cov; extra == "test"
Dynamic: license-file
